zodchy_transport/__init__.py
zodchy_transport/consumers/__init__.py
zodchy_transport/consumers/rabbitmq.py
zodchy_transport/dispatchers/__init__.py
zodchy_transport/dispatchers/rabbitmq.py
zodchy_transport-0.1.3.dist-info/METADATA
zodchy_transport-0.1.3.dist-info/WHEEL
zodchy_transport-0.1.3.dist-info/RECORD
